ipodshuffle-0.4.1.dist-info/top_level.txt
ipodshuffle-0.4.1.dist-info/metadata.json
ipodshuffle-0.4.1.dist-info/RECORD
ipodshuffle-0.4.1.dist-info/METADATA
ipodshuffle-0.4.1.dist-info/WHEEL
ipodshuffle-0.4.1.dist-info/DESCRIPTION.rst
ipodshuffle-0.4.1.dist-info/entry_points.txt
teresa/__init__.py
teresa/__main__.py
teresa/sync.py
teresa/utils.py
teresa/fix_zh.py
teresa/show.py
teresa/version.py
teresa/set_.py
teresa/tts/__init__.py
teresa/tts/error.py
teresa/tts/voicerss.py
teresa/tts/svox.py
teresa/locale/zh_CN/LC_MESSAGES/teresa.mo
teresa/locale/zh_CN/LC_MESSAGES/teresa.po
ipodshuffle-0.4.1.data/data/share/locale/zh_CN/LC_MESSAGES/teresa.mo
ipodshuffle/audio.py
ipodshuffle/__init__.py
ipodshuffle/message.py
ipodshuffle/shuffle.py
ipodshuffle/utils.py
ipodshuffle/version.py
ipodshuffle/db/__init__.py
ipodshuffle/db/itunesstats.py
ipodshuffle/db/db.py
ipodshuffle/db/itunessd.py
ipodshuffle/storage/local.py
ipodshuffle/storage/__init__.py
ipodshuffle/storage/voice.py
ipodshuffle/storage/log.py
