Metadata-Version: 2.0
Name: ipodshuffle
Version: 0.4.1
Summary: modules and tools for iPod shuffle 4th generation
Home-page: https://github.com/meng89/ipodshuffle
Author: Chen Meng
Author-email: ObserverChan@gmail.com
License: MIT
Platform: UNKNOWN
Classifier: Development Status :: 4 - Beta
Classifier: Intended Audience :: Developers
Classifier: License :: OSI Approved :: MIT License
Classifier: Programming Language :: Python :: 3
Classifier: Topic :: Software Development :: Libraries :: Python Modules
Requires-Dist: langid (>=1.1.5)
Requires-Dist: mutagen (>=1.27)
Requires-Dist: Babel
